[
  {
    "employeeId": "NGM00136",
    "name": "VIVEK BHARTI",
    "email": "edp.ngm2@pgel.in",
    "phone": "8210496005",
    "department": "IT",
    "location": "BHIWADI",
    "designation": "ENGINNER",
    "plant": "4020",
    "status": "Active",
    "createdAt": "2026-06-20T05:08:56.391Z",
    "updatedAt": "2026-06-29T16:22:09.035Z"
  },
  {
    "employeeId": "NGM00138",
    "name": "KS",
    "email": "ks.2@pgel.in",
    "phone": "9876567987",
    "department": "Finance",
    "location": "BHIWADI",
    "designation": "employe",
    "plant": "4020",
    "status": "Active",
    "createdAt": "2026-06-20T10:45:15.959Z",
    "updatedAt": "2026-06-29T16:22:09.035Z"
  },
  {
    "employeeId": "NGM00234",
    "name": "Manoj",
    "email": "vikas@pgel.in",
    "phone": "8765698769",
    "department": "Engineering",
    "location": "BHIWADI",
    "designation": "employe",
    "plant": "4020",
    "status": "Active",
    "createdAt": "2026-06-23T09:50:27.524Z",
    "updatedAt": "2026-06-29T16:22:09.035Z"
  },
  {
    "employeeId": "NGM00134",
    "name": "himanshu",
    "email": "edp.ngm2@pgel.in",
    "phone": "6350039958",
    "department": "IT",
    "location": "BHIWADI",
    "designation": "trainee",
    "plant": "4020",
    "status": "Active",
    "createdAt": "2026-06-27T11:47:23.156Z",
    "updatedAt": "2026-06-29T16:22:09.035Z"
  },
  {
    "employeeId": "PT500162",
    "name": "KUSHAGAR GAUTAM",
    "email": "hr.ngm2@pgel.in",
    "phone": "9870696547",
    "department": "HR",
    "location": "BHIWADI",
    "designation": "EXECUTIVE",
    "plant": "4020",
    "status": "Active",
    "createdAt": "2026-06-29T09:02:47.885Z",
    "updatedAt": "2026-06-29T16:22:09.035Z"
  },
  {
    "employeeId": "NGM00027",
    "name": "VISHVAS SHARMA",
    "email": "prod.ngm2@pgel.in",
    "phone": "7053727784",
    "department": "Production",
    "location": "BHIWADI",
    "designation": "ENG",
    "plant": "4020",
    "status": "Active",
    "createdAt": "2026-06-29T09:22:44.796Z",
    "updatedAt": "2026-06-29T16:22:09.035Z"
  },
  {
    "employeeId": "BM00473",
    "name": "NITIN VERMA",
    "email": "ppc.ngm2@pgel.in",
    "phone": "8433301238",
    "department": "MOLDING",
    "location": "BHIWADI",
    "designation": "EXECUTIVE",
    "plant": "4020",
    "status": "Active",
    "createdAt": "2026-06-29T09:38:54.981Z",
    "updatedAt": "2026-06-29T16:22:09.035Z"
  },
  {
    "employeeId": "PT500106",
    "name": "AMIT BARWAL",
    "email": "amit.barwal@pgel.in",
    "phone": "8580752476",
    "department": "RND",
    "location": "BHIWADI",
    "designation": "AM",
    "plant": "4020",
    "status": "Active",
    "createdAt": "2026-06-29T09:49:51.217Z",
    "updatedAt": "2026-06-29T16:22:09.035Z"
  },
  {
    "employeeId": "NGM00028",
    "name": "DINESH YADAV",
    "email": "sap.support4020@pgel.in",
    "phone": "9466380343",
    "department": "IT SAP",
    "location": "BHIWADI",
    "designation": "ENGINEER",
    "plant": "4020",
    "status": "Active",
    "createdAt": "2026-06-29T10:28:45.553Z",
    "updatedAt": "2026-06-29T16:22:09.035Z"
  },
  {
    "employeeId": "PT500051",
    "name": "VIJAY YADAV",
    "email": "innovation.pgtl8@pgel.in",
    "phone": "6386540623",
    "department": "INNOVATION",
    "location": "BHIWADI",
    "designation": "ENGG",
    "plant": "4020",
    "status": "Active",
    "createdAt": "2026-06-29T10:36:20.870Z",
    "updatedAt": "2026-06-29T16:22:09.035Z"
  },
  {
    "employeeId": "PT500312",
    "name": "MONIKA BONDRE",
    "email": "monika.bondre8@pgel.in",
    "phone": "9028657981",
    "department": "INNOVATION",
    "location": "BHIWADI",
    "designation": "SR. ENG.",
    "plant": "2040",
    "status": "Active",
    "createdAt": "2026-06-29T11:19:48.319Z",
    "updatedAt": "2026-06-29T16:22:09.035Z"
  },
  {
    "employeeId": "NGM00021",
    "name": "PANKAJ",
    "email": "store.ngm2@pgel.in",
    "phone": "9996904888",
    "department": "Store",
    "location": "BHIWADI",
    "designation": "EXE",
    "plant": "4020",
    "status": "Active",
    "createdAt": "2026-06-29T11:27:38.359Z",
    "updatedAt": "2026-06-29T16:22:09.035Z"
  },
  {
    "employeeId": "PT500251",
    "name": "NITESH",
    "email": "logistics.ngm2@pgel.in",
    "phone": "9350076558",
    "department": "DISPATCH",
    "location": "BHIWADI",
    "designation": "EXE",
    "plant": "4020",
    "status": "Active",
    "createdAt": "2026-06-29T11:41:22.597Z",
    "updatedAt": "2026-06-29T16:22:09.035Z"
  },
  {
    "employeeId": "PT500163",
    "name": "ANAND ARYA",
    "email": "anand.arya7@pgel.in",
    "phone": "9354264668",
    "department": "IT",
    "location": "BHIWADI",
    "designation": "SR.MANAGER",
    "plant": "4020",
    "status": "Active",
    "createdAt": "2026-06-29T15:18:33.959Z",
    "updatedAt": "2026-06-29T16:22:09.035Z"
  },
  {
    "employeeId": "PT500057",
    "name": "ANIL KUMAR",
    "email": "anil.purchase8@pgel.in",
    "phone": "8398999907",
    "department": "Purchase",
    "location": "BHIWADI",
    "designation": "SR.EXECUTIVE",
    "plant": "4020",
    "status": "Active",
    "createdAt": "2026-06-29T15:27:18.075Z",
    "updatedAt": "2026-06-29T16:22:09.035Z"
  },
  {
    "employeeId": "NGM00091",
    "name": "RAJENDER SONI",
    "email": "rajender.soni8@pgel.in",
    "phone": "9319244365",
    "department": "Purchase",
    "location": "BHIWADI",
    "designation": "MANAGER",
    "plant": "4020",
    "status": "Active",
    "createdAt": "2026-06-29T15:32:44.929Z",
    "updatedAt": "2026-06-29T16:22:09.035Z"
  },
  {
    "employeeId": "PGTL0045",
    "name": "SACHIN",
    "email": "sachin.01@pgel.in",
    "phone": "8765787678",
    "department": "ppc",
    "location": "BHIWADI",
    "designation": "emp",
    "plant": "2040",
    "status": "Active",
    "syncSheet": true,
    "updatedAt": "2026-06-29T16:22:09.035Z",
    "createdAt": "2026-06-29T16:07:43.775Z"
  }
]